dbdpy.py
dbdpy-1.2.9.dist-info/WHEEL
dbdpy-1.2.9.dist-info/METADATA
dbdpy-1.2.9.dist-info/RECORD
